pdpc_decisions/__init__.py
pdpc_decisions/download_file.py
pdpc_decisions/pdpcdecision.py
pdpc_decisions/save_file.py
pdpc_decisions/scraper.py
pdpc_decisions/scraper_extras.py
pdpc_decisions-1.1.0.dist-info/LICENSE
pdpc_decisions-1.1.0.dist-info/METADATA
pdpc_decisions-1.1.0.dist-info/WHEEL
pdpc_decisions-1.1.0.dist-info/top_level.txt
pdpc_decisions-1.1.0.dist-info/RECORD
