Metadata-Version: 2.1
Name: pdpc-decisions
Version: 1.1.0
Summary: Tools to extract and compile enforcement decisions from the Singapore Personal Data Protection Commission
Home-page: https://github.com/houfu/pdpc-decisions/
Author: Ang Houfu 
Author-email: houfu@outlook.sg
License: UNKNOWN
Platform: UNKNOWN
Classifier: Development Status :: 5 - Production/Stable
Requires-Python: >=3.6
Requires-Dist: Click
Requires-Dist: selenium
Requires-Dist: beautifulsoup4
Requires-Dist: pdfminer.six
Requires-Dist: html5lib
Requires-Dist: requests
Requires-Dist: spacy
